metapensiero/sqlalchemy/dbloady/__init__.py
metapensiero/sqlalchemy/dbloady/dump.py
metapensiero/sqlalchemy/dbloady/entity.py
metapensiero/sqlalchemy/dbloady/load.py
metapensiero_sqlalchemy_dbloady-3.1.dist-info/METADATA
metapensiero_sqlalchemy_dbloady-3.1.dist-info/WHEEL
metapensiero_sqlalchemy_dbloady-3.1.dist-info/entry_points.txt
metapensiero_sqlalchemy_dbloady-3.1.dist-info/RECORD
