Metadata-Version: 2.1
Name: metapensiero.sqlalchemy.dbloady
Version: 3.1
Summary: YAML based data loader
Keywords: YAML,Jinja2,scaffolding,skeleton
Author-Email: Lele Gaifax <lele@metapensiero.it>
License: GPL-3.0-or-later
Classifier: Environment :: Console
Classifier: Programming Language :: Python
Classifier: Programming Language :: Python :: 3
Classifier: Programming Language :: Python :: 3 :: Only
Classifier: Programming Language :: Python :: 3.11
Classifier: Programming Language :: Python :: 3.12
Classifier: Development Status :: 5 - Production/Stable
Classifier: Intended Audience :: Developers
Classifier: License :: OSI Approved :: GNU General Public License v3 or later (GPLv3+)
Classifier: Topic :: Database
Classifier: Topic :: Utilities
Project-URL: Changelog, https://gitlab.com/metapensiero/metapensiero.sqlalchemy.dbloady/-/blob/master/CHANGES.rst
Project-URL: Source, https://gitlab.com/metapensiero/metapensiero.sqlalchemy.dbloady
Requires-Python: >=3.9
Requires-Dist: progressbar2
Requires-Dist: ruamel.yaml
Requires-Dist: sqlalchemy
Provides-Extra: dev
Requires-Dist: build; extra == "dev"
Requires-Dist: bump-my-version; extra == "dev"
Requires-Dist: twine; extra == "dev"
